LICENSE
MANIFEST.in
README.md
setup.py
tabler_qicon.egg-info/PKG-INFO
tabler_qicon.egg-info/SOURCES.txt
tabler_qicon.egg-info/dependency_links.txt
tabler_qicon.egg-info/requires.txt
tabler_qicon.egg-info/top_level.txt
tablerqicon/__init__.py
tablerqicon/__init__.pyi
tablerqicon/extended_tablerqicon.pyi
tablerqicon/tablerqicon.py
tablerqicon/icons/12-hours.svg
tablerqicon/icons/123.svg
tablerqicon/icons/24-hours.svg
tablerqicon/icons/2fa.svg
tablerqicon/icons/360-view.svg
tablerqicon/icons/360.svg
tablerqicon/icons/3d-cube-sphere-off.svg
tablerqicon/icons/3d-cube-sphere.svg
tablerqicon/icons/3d-rotate.svg
tablerqicon/icons/a-b-2.svg
tablerqicon/icons/a-b-off.svg
tablerqicon/icons/a-b.svg
tablerqicon/icons/abacus-off.svg
tablerqicon/icons/abacus.svg
tablerqicon/icons/abc.svg
tablerqicon/icons/access-point-off.svg
tablerqicon/icons/access-point.svg
tablerqicon/icons/accessible-off-filled.svg
tablerqicon/icons/accessible-off.svg
tablerqicon/icons/accessible.svg
tablerqicon/icons/activity-heartbeat.svg
tablerqicon/icons/activity.svg
tablerqicon/icons/ad-2.svg
tablerqicon/icons/ad-circle-filled.svg
tablerqicon/icons/ad-circle-off.svg
tablerqicon/icons/ad-circle.svg
tablerqicon/icons/ad-filled.svg
tablerqicon/icons/ad-off.svg
tablerqicon/icons/ad.svg
tablerqicon/icons/address-book-off.svg
tablerqicon/icons/address-book.svg
tablerqicon/icons/adjustments-alt.svg
tablerqicon/icons/adjustments-bolt.svg
tablerqicon/icons/adjustments-cancel.svg
tablerqicon/icons/adjustments-check.svg
tablerqicon/icons/adjustments-code.svg
tablerqicon/icons/adjustments-cog.svg
tablerqicon/icons/adjustments-dollar.svg
tablerqicon/icons/adjustments-down.svg
tablerqicon/icons/adjustments-exclamation.svg
tablerqicon/icons/adjustments-filled.svg
tablerqicon/icons/adjustments-heart.svg
tablerqicon/icons/adjustments-horizontal.svg
tablerqicon/icons/adjustments-minus.svg
tablerqicon/icons/adjustments-off.svg
tablerqicon/icons/adjustments-pause.svg
tablerqicon/icons/adjustments-pin.svg
tablerqicon/icons/adjustments-plus.svg
tablerqicon/icons/adjustments-question.svg
tablerqicon/icons/adjustments-search.svg
tablerqicon/icons/adjustments-share.svg
