Metadata-Version: 2.1
Name: tabler-qicon
Version: 0.2.3
Summary: Python package that provides easy access to Tabler Icons for PyQt and PySide applications.
Home-page: https://github.com/promto-c/tabler-qicon
Author: Charin Rungchaowarat
License: MIT
Classifier: Development Status :: 5 - Production/Stable
Classifier: Intended Audience :: Developers
Classifier: License :: OSI Approved :: MIT License
Classifier: Operating System :: OS Independent
Classifier: Programming Language :: Python :: 3.6
Classifier: Programming Language :: Python :: 3.7
Classifier: Programming Language :: Python :: 3.8
Classifier: Programming Language :: Python :: 3.9
Classifier: Programming Language :: Python :: 3.10
Classifier: Topic :: Software Development :: Libraries
Classifier: Topic :: Software Development :: Libraries :: Python Modules
Classifier: Natural Language :: English
Classifier: Typing :: Typed
Requires-Python: >=3.6
Provides-Extra: PyQt5
Provides-Extra: PyQt6
Provides-Extra: PySide2
Provides-Extra: PySide6
License-File: LICENSE
